agentd/__init__.py
agentd/client.py
agentd/config.py
agentd/models.py
agentd/tracker.py
agentd/transport.py
agentd_sdk-0.6.0.dist-info/METADATA
agentd_sdk-0.6.0.dist-info/WHEEL
agentd_sdk-0.6.0.dist-info/licenses/LICENSE
agentd_sdk-0.6.0.dist-info/RECORD
