Metadata-Version: 2.4
Name: agentd-sdk
Version: 0.6.0
Summary: Observability SDK for Claude Agent SDK - metrics, tracing, and debugging for AI agents
Project-URL: Homepage, https://github.com/getagentd/agentd-py
Project-URL: Documentation, https://github.com/getagentd/agentd-py#readme
Project-URL: Repository, https://github.com/getagentd/agentd-py
Project-URL: Issues, https://github.com/getagentd/agentd-py/issues
Author-email: Arth <probablyarth@gmail.com>
License-Expression: MIT
License-File: LICENSE
Keywords: agents,ai,anthropic,claude,metrics,observability,tracing
Classifier: Development Status :: 3 - Alpha
Classifier: Intended Audience :: Developers
Classifier: License :: OSI Approved :: MIT License
Classifier: Programming Language :: Python :: 3
Classifier: Programming Language :: Python :: 3.10
Classifier: Programming Language :: Python :: 3.11
Classifier: Programming Language :: Python :: 3.12
Classifier: Topic :: Software Development :: Libraries :: Python Modules
Classifier: Topic :: System :: Monitoring
Requires-Python: >=3.10
Requires-Dist: aiohttp>=3.8.0
Provides-Extra: aiohttp
Requires-Dist: aiohttp>=3.8.0; extra == 'aiohttp'
Provides-Extra: dev
Requires-Dist: black>=23.0.0; extra == 'dev'
Requires-Dist: mypy>=1.0.0; extra == 'dev'
Requires-Dist: pytest-asyncio>=0.21.0; extra == 'dev'
Requires-Dist: pytest>=7.0.0; extra == 'dev'
Requires-Dist: ruff>=0.0.270; extra == 'dev'
Provides-Extra: full
Requires-Dist: aiohttp>=3.8.0; extra == 'full'
Requires-Dist: claude-agent-sdk>=0.1.3; extra == 'full'
Provides-Extra: httpx
Requires-Dist: httpx>=0.24.0; extra == 'httpx'
Provides-Extra: requests
Requires-Dist: requests>=2.28.0; extra == 'requests'
Provides-Extra: sdk
Requires-Dist: claude-agent-sdk>=0.1.3; extra == 'sdk'
